igeVmath.cpython-39-darwin.so
igeVmath-0.7.0.dist-info/LICENSE
igeVmath-0.7.0.dist-info/METADATA
igeVmath-0.7.0.dist-info/WHEEL
igeVmath-0.7.0.dist-info/top_level.txt
igeVmath-0.7.0.dist-info/RECORD
