Metadata-Version: 2.1
Name: igeVmath
Version: 0.7.0
Summary: C++ Vector Math extension for 3D and 2D games.
Home-page: https://indigames.net/
Author: Indigames
Author-email: dev@indigames.net
License: MIT
Keywords: Vector Math 3D game Indigames
Classifier: Intended Audience :: Developers
Classifier: License :: OSI Approved :: MIT License
Classifier: Programming Language :: Python :: 3
Classifier: Operating System :: Microsoft :: Windows
Classifier: Topic :: Games/Entertainment
License-File: LICENSE
